{
  "isscc-2027::https://www.isscc.org/paper-submission": {
    "hash": "ac332adbb4669f23",
    "keywords": {
      "Deadline for Electronic Submission": true,
      "September 9, 2026": true,
      "February 14-18, 2027": false
    },
    "checkedAt": 1782793339
  },
  "isscc-2027::https://www.isscc.org/call-for-papers-overview": {
    "hash": "10086bb345a7ab99",
    "keywords": {
      "Deadline for Electronic Submission": false,
      "September 9, 2026": false,
      "February 14-18, 2027": true
    },
    "checkedAt": 1782793339
  },
  "vlsi-2026::https://www.vlsisymposium.org/": {
    "hash": "0e6b9581c386614c",
    "keywords": {
      "Submission Deadline": false,
      "Late News": true,
      "JUNE 14-18, 2026": true
    },
    "checkedAt": 1784691632
  },
  "vlsi-2026::https://www.vlsisymposium.org/call-for-papers/": {
    "hash": "5db36528379058fc",
    "keywords": {
      "Submission Deadline": true,
      "Late News": true,
      "JUNE 14-18, 2026": false
    },
    "checkedAt": 1784691632
  },
  "esserc-2026::https://www.esserc2026.org/": {
    "hash": "b2bdb93bd28189f9",
    "keywords": {
      "PAPERS SUBMISSION DEADLINE": false,
      "APRIL 10, 2026": false,
      "September 7-10, 2026": true
    },
    "checkedAt": 1784691632
  },
  "esserc-2026::https://www.esserc2026.org/papers": {
    "hash": "31983781a3ad7cd2",
    "keywords": {
      "PAPERS SUBMISSION DEADLINE": true,
      "APRIL 10, 2026": true,
      "September 7-10, 2026": false
    },
    "checkedAt": 1784691633
  },
  "esserc-2026::https://www.esserc2026.org/venue": {
    "hash": "fcf3af09a5d5aa5e",
    "keywords": {
      "PAPERS SUBMISSION DEADLINE": false,
      "APRIL 10, 2026": false,
      "September 7-10, 2026": false
    },
    "checkedAt": 1784519979
  },
  "asscc-2026::https://www.a-sscc2026.org/": {
    "hash": "a6338698e2ae2954",
    "keywords": {
      "submission deadline has been extended": true,
      "June 14, 2026": true,
      "The Lin Hotel": false
    },
    "checkedAt": 1784691634
  },
  "asscc-2026::https://www.a-sscc2026.org/venue-for-the-conference": {
    "hash": "1f7cf581d19b3609",
    "keywords": {
      "submission deadline has been extended": false,
      "June 14, 2026": false,
      "The Lin Hotel": true
    },
    "checkedAt": 1784691636
  },
  "isca-2026::https://iscaconf.org/isca2026/": {
    "hash": "9ed781e649989161",
    "keywords": {
      "Important Dates": false,
      "Full Paper Deadline": false,
      "June 27": true
    },
    "checkedAt": 1784691637
  },
  "isca-2026::https://iscaconf.org/isca2026/submit/callforpapers.php": {
    "hash": "70165c921875f1a1",
    "keywords": {
      "Important Dates": true,
      "Full Paper Deadline": true,
      "June 27": true
    },
    "checkedAt": 1784691637
  },
  "hpca-2027::https://conf.researchr.org/track/hpca-2027/hpca-2027-main-conference": {
    "hash": "edefce01710fb70d",
    "keywords": {
      "Paper Registration and Abstract Submission": true,
      "Paper Submission": true,
      "under construction": false
    },
    "checkedAt": 1784691637
  },
  "asplos-2027-april::https://www.asplos-conference.org/asplos2027/cfp/": {
    "hash": "46dad37899ef8ab6",
    "keywords": {
      "Full paper submission": true,
      "April 15, 2026": true,
      "September 9, 2026": true
    },
    "checkedAt": 1784691638
  },
  "asplos-2027-april::https://www.asplos-conference.org/": {
    "hash": "c4d0c6a1deb23990",
    "keywords": {
      "Full paper submission": false,
      "April 15, 2026": false,
      "September 9, 2026": false
    },
    "checkedAt": 1784691638
  },
  "micro-2026::https://www.microarch.org/micro59/": {
    "hash": "1eef1b218f71c15b",
    "keywords": {
      "Abstract Deadline": true,
      "Full Paper Deadline": true,
      "October 31": true
    },
    "checkedAt": 1784691638
  },
  "micro-2026::https://www.microarch.org/micro59/submit/papers.php": {
    "hash": "d6eef0c5bc0ac50b",
    "keywords": {
      "Abstract Deadline": true,
      "Full Paper Deadline": true,
      "October 31": true
    },
    "checkedAt": 1784691638
  }
}
